resiliencepy/__init__.py
resiliencepy/disruptions.py
resiliencepy/engine.py
resiliencepy/metrics.py
resiliencepy/policies.py
resiliencepy/registry.py
resiliencepy/series.py
resiliencepy/types.py
resiliencepy-0.1.0.dist-info/METADATA
resiliencepy-0.1.0.dist-info/WHEEL
resiliencepy-0.1.0.dist-info/top_level.txt
resiliencepy-0.1.0.dist-info/RECORD
