Metadata-Version: 2.4
Name: resiliencepy
Version: 0.1.0
Summary: A recovery-centric, metric-standardized Python core for supply chain resilience modeling.
Author: Ramakrishna Garine
License: MIT
Requires-Python: >=3.9
Requires-Dist: numpy>=1.22
Provides-Extra: plot
Requires-Dist: matplotlib>=3.6; extra == "plot"
Provides-Extra: dev
Requires-Dist: pytest>=7; extra == "dev"
Requires-Dist: ruff>=0.4; extra == "dev"
Requires-Dist: mypy>=1.7; extra == "dev"
